asn1vnparser/__init__.py
asn1vnparser/_asn1vnparser.py
asn1vnparser/_grammar.py
asn1vnparser/cli.py
asn1vnparser/jsonencoder.py
asn1vnparser-0.2.3.dist-info/LICENSE
asn1vnparser-0.2.3.dist-info/METADATA
asn1vnparser-0.2.3.dist-info/WHEEL
asn1vnparser-0.2.3.dist-info/entry_points.txt
asn1vnparser-0.2.3.dist-info/top_level.txt
asn1vnparser-0.2.3.dist-info/RECORD
