Metadata-Version: 2.1
Name: asn1vnparser
Version: 0.2.3
Summary: Parses ASN.1 value notation into a Python object or JSON without requiring its ASN.1 schema.
Home-page: https://github.com/mtannaan/asn1vnparser
Author: mtannaan
Author-email: 12782884+mtannaan@users.noreply.github.com
License: ISC license
Keywords: asn1vnparser
Platform: UNKNOWN
Classifier: Development Status :: 4 - Beta
Classifier: Intended Audience :: Developers
Classifier: License :: OSI Approved :: ISC License (ISCL)
Classifier: Natural Language :: English
Classifier: Programming Language :: Python :: 3
Classifier: Programming Language :: Python :: 3.6
Classifier: Programming Language :: Python :: 3.7
Requires-Python: !=3.0.*, !=3.1.*, !=3.2.*, !=3.3.*, !=3.4.*
License-File: LICENSE
Requires-Dist: bitarray (>=0.8.3)
Requires-Dist: pyparsing (<3,>=2.4.2)
